{"date":"22/04/2023","readingOfToday":{"title":"Lectura del libro de los Hechos de los apóstoles ","book":"Hch 6, 1-7","content":"En aquellos días, como aumentaba mucho el número de los discípulos, hubo ciertas quejas de los judíos griegos contra los hebreos, de que no se atendía bien a sus viudas en el servicio de caridad de todos los días.  Los Doce convocaron entonces a la multitud de los discípulos y les dijeron: “No es justo que, dejando el ministerio de la palabra de Dios, nos dediquemos a administrar los bienes. Escojan entre ustedes a siete hombres de buena reputación, llenos del Espíritu Santo y de sabiduría, a los cuales encargaremos este servicio. Nosotros nos dedicaremos a la oración y al servicio de la palabra”.  Todos estuvieron de acuerdo y eligieron a Esteban, hombre lleno de fe y del Espíritu Santo, a Felipe, Prócoro, Nicanor, Timón, Pármenas y Nicolás, prosélito de Antioquía. Se los presentaron a los apóstoles, y éstos, después de haber orado, les impusieron las manos.  Mientras tanto, la palabra de Dios iba cundiendo. En Jerusalén se multiplicaba grandemente el número de los discípulos. Incluso un grupo numeroso de sacerdotes había aceptado la fe. "},"gospelOfTheDay":{"title":"Lectura del santo evangelio según san Juan ","book":"Jn 6, 16-21","content":"Al atardecer del día de la multiplicación de los panes, los discípulos de Jesús bajaron al lago, se embarcaron y empezaron a atravesar hacia Cafarnaúm. Ya había caído la noche y Jesús todavía no los había alcanzado. Soplaba un viento fuerte y las aguas del lago se iban encrespando.  Cuando habían avanzado unos cinco o seis kilómetros, vieron a Jesús caminando sobre las aguas, acercándose a la barca, y se asustaron. Pero él les dijo: “Soy yo, no tengan miedo”. Ellos quisieron recogerlo a bordo y rápidamente la barca tocó tierra en el lugar a donde se dirigían."}}