[{"id":"3095522940133717260","pictures":"https://scontent-iad3-2.cdninstagram.com/v/t51.2885-15/344578632_528603772608939_6702985190009468156_n.webp?stp=dst-jpg_e35&_nc_ht=scontent-iad3-2.cdninstagram.com&_nc_cat=103&_nc_ohc=lnVZPSwnjDIAX_O9iny&edm=APU89FABAAAA&ccb=7-5&ig_cache_key=MzA5NTUyMjkzNDIzNjQ0ODE3Ng%3D%3D.2-ccb7-5&oh=00_AfDovDdp-Xp4BGcpLD_jdkJNuBYVgIYTjvcGpfmKNATErw&oe=64630496&_nc_sid=86f79a"},{"id":"3094709379895181480","pictures":"https://scontent-iad3-2.cdninstagram.com/v/t51.2885-15/345025867_1585784225243871_2733132503802474760_n.webp?stp=dst-jpg_e35&_nc_ht=scontent-iad3-2.cdninstagram.com&_nc_cat=103&_nc_ohc=wMrOzjrB50sAX8VpZoR&edm=APU89FABAAAA&ccb=7-5&ig_cache_key=MzA5NDcwOTM3OTg5NTE4MTQ4MA%3D%3D.2-ccb7-5&oh=00_AfAojfl3FtJz5rQLBvYrQRs0hfZxXZrvudeIi5eZPYwRsw&oe=64635FAC&_nc_sid=86f79a"},{"id":"3093284618245803580","pictures":"https://scontent-iad3-2.cdninstagram.com/v/t51.2885-15/344553948_197740969739472_6876540254203201706_n.webp?stp=dst-jpg_e35&_nc_ht=scontent-iad3-2.cdninstagram.com&_nc_cat=100&_nc_ohc=Ti92v0yKYLYAX8sp1C8&edm=APU89FABAAAA&ccb=7-5&ig_cache_key=MzA5MzI4NDYxODI0NTgwMzU4MA%3D%3D.2-ccb7-5&oh=00_AfAm9udbBKXoAH-fLXKkTYYcLdUX_jEAkUruJVpC3z6ukg&oe=646253D1&_nc_sid=86f79a"},{"id":"3093138830253534367","pictures":"https://scontent-iad3-1.cdninstagram.com/v/t51.2885-15/344173677_792101979112114_5062795211153346023_n.webp?stp=dst-jpg_e35&_nc_ht=scontent-iad3-1.cdninstagram.com&_nc_cat=110&_nc_ohc=zczzqTHW2uUAX9U1B3r&edm=APU89FABAAAA&ccb=7-5&ig_cache_key=MzA5MzEzODgzMDI1MzUzNDM2Nw%3D%3D.2-ccb7-5&oh=00_AfCWPOmGk5NkVgao6FfQwznU3IZmrt9zqO02o_VB9rdPIA&oe=64632F68&_nc_sid=86f79a"},{"id":"3082344423031883874","pictures":"https://scontent-iad3-1.cdninstagram.com/v/t51.2885-15/328341117_947158293380510_5348614167709273928_n.webp?stp=dst-jpg_e35&_nc_ht=scontent-iad3-1.cdninstagram.com&_nc_cat=102&_nc_ohc=YC1aVJG1WsUAX8szY49&edm=APU89FABAAAA&ccb=7-5&ig_cache_key=MzA4MjM0NDQxNzUwMzc3NjkzMA%3D%3D.2-ccb7-5&oh=00_AfDaHdbWeo0foUcGK919DQpqAmXqqhzjALJw7pus0Pykig&oe=6463F99B&_nc_sid=86f79a"},{"id":"3082236523127090054","pictures":"https://scontent-iad3-1.cdninstagram.com/v/t51.2885-15/341586044_533688895593571_2970840009187163550_n.webp?stp=dst-jpg_e35&_nc_ht=scontent-iad3-1.cdninstagram.com&_nc_cat=107&_nc_ohc=zUIPoXpX8gAAX9HzPve&edm=APU89FABAAAA&ccb=7-5&ig_cache_key=MzA4MjIzNjUyMzEyNzA5MDA1NA%3D%3D.2-ccb7-5&oh=00_AfDR8mDhDaO58fF1KfQOi2AojR6wD80-IZy5tROJ2nnKyQ&oe=64637051&_nc_sid=86f79a"},{"id":"3077412803673933050","pictures":"https://scontent-iad3-2.cdninstagram.com/v/t51.2885-15/340160248_1334235187432763_1095476699837930138_n.webp?stp=dst-jpg_e35&_nc_ht=scontent-iad3-2.cdninstagram.com&_nc_cat=111&_nc_ohc=u8GWtKKuiP0AX-v_Fvb&edm=APU89FABAAAA&ccb=7-5&ig_cache_key=MzA3NzQxMjgwMzY3MzkzMzA1MA%3D%3D.2-ccb7-5&oh=00_AfCcXj43z9NPPrmebJyBLHQ0hIeNXusN5yMk6W2V7XalvA&oe=646302D0&_nc_sid=86f79a"},{"id":"3077405593120094821","pictures":"https://scontent-iad3-1.cdninstagram.com/v/t51.2885-15/340175130_572728651501718_7861409328666524617_n.webp?stp=dst-jpg_e35&_nc_ht=scontent-iad3-1.cdninstagram.com&_nc_cat=102&_nc_ohc=Q-oGf0GdhYIAX_MAVmU&edm=APU89FABAAAA&ccb=7-5&ig_cache_key=MzA3NzQwNTU5MzEyMDA5NDgyMQ%3D%3D.2-ccb7-5&oh=00_AfCm977oZoxC16fUDgKbbKd2xNopOkCRVSnHxtuRFwnjJw&oe=6463FFA8&_nc_sid=86f79a"},{"id":"3077398913380644988","pictures":"https://scontent-iad3-1.cdninstagram.com/v/t51.2885-15/340653832_263826449319896_1165135371871733392_n.webp?stp=dst-jpg_e35&_nc_ht=scontent-iad3-1.cdninstagram.com&_nc_cat=108&_nc_ohc=V15dVmDMAMQAX-plqGH&edm=APU89FABAAAA&ccb=7-5&ig_cache_key=MzA3NzM5ODkxMzM4MDY0NDk4OA%3D%3D.2-ccb7-5&oh=00_AfCQ1G-STw0YqUDNrlAm1f13HfGYJeFvZVatCTAWrdGy_g&oe=64631E62&_nc_sid=86f79a"},{"id":"3077183728556567257","pictures":"https://scontent-iad3-2.cdninstagram.com/v/t51.2885-15/340178038_926939471905686_1386896573733632857_n.jpg?stp=dst-jpg_e15&_nc_ht=scontent-iad3-2.cdninstagram.com&_nc_cat=106&_nc_ohc=FXRoCuKNmyQAX_VnfXa&edm=APU89FABAAAA&ccb=7-5&oh=00_AfCDNAoqUt_yJyxAG-XDBc_Oo-3GnVocIZRab9PSy_o6TA&oe=6460043D&_nc_sid=86f79a"},{"id":"3076620312800643143","pictures":"https://scontent-iad3-1.cdninstagram.com/v/t51.2885-15/340334429_945527096633402_2251344375844282067_n.webp?stp=dst-jpg_e35&_nc_ht=scontent-iad3-1.cdninstagram.com&_nc_cat=102&_nc_ohc=y66M53JSHVoAX9t8wc5&edm=APU89FABAAAA&ccb=7-5&ig_cache_key=MzA3NjYyMDMxMjgwMDY0MzE0Mw%3D%3D.2-ccb7-5&oh=00_AfCU2RSlSE1Jh7XQA-zq60YhPZIPWUQJLc8Vr0uFa_qRpw&oe=6462C94B&_nc_sid=86f79a"},{"id":"3076039130694214531","pictures":"https://scontent-iad3-1.cdninstagram.com/v/t51.2885-15/339829528_1163641847662606_7723495676839436787_n.webp?stp=dst-jpg_e35&_nc_ht=scontent-iad3-1.cdninstagram.com&_nc_cat=110&_nc_ohc=wlNHHw6QNGUAX9Ihlf2&edm=APU89FABAAAA&ccb=7-5&ig_cache_key=MzA3NjAzOTEyNDQ3ODI0MTUzMg%3D%3D.2-ccb7-5&oh=00_AfA8IWpvUElgA_M0L5H4qnW6V5plZqx1aQ-00yqENvKjhg&oe=6463C6BF&_nc_sid=86f79a"},{"id":"3076023385016983734","pictures":"https://scontent-iad3-2.cdninstagram.com/v/t51.2885-15/339998326_762589435468451_7355595665232484760_n.webp?stp=dst-jpg_e35&_nc_ht=scontent-iad3-2.cdninstagram.com&_nc_cat=111&_nc_ohc=k3NVkd84VgIAX8uRazJ&edm=APU89FABAAAA&ccb=7-5&ig_cache_key=MzA3NjAyMzM3ODIzMDM3OTU2Mw%3D%3D.2-ccb7-5&oh=00_AfD78CrdUmbwmvs2DnRBK9AP8XQxahHuC6h8Qb-d8rHzeA&oe=6463ACCE&_nc_sid=86f79a"},{"id":"3075665891576973368","pictures":"https://scontent-iad3-1.cdninstagram.com/v/t51.2885-15/339865729_930835888042243_7441994661172486693_n.webp?stp=dst-jpg_e35&_nc_ht=scontent-iad3-1.cdninstagram.com&_nc_cat=107&_nc_ohc=3zv0OWwo714AX8Vnp9g&edm=APU89FABAAAA&ccb=7-5&ig_cache_key=MzA3NTY2NTg5MTU3Njk3MzM2OA%3D%3D.2-ccb7-5&oh=00_AfAcM58ezVxsgarFIAKlUio2BUNxwcE84fDJvNFAvjTqFw&oe=64635924&_nc_sid=86f79a"},{"id":"3075382536083986280","pictures":"https://scontent-iad3-2.cdninstagram.com/v/t51.2885-15/339674169_236374522210847_964000247987090615_n.webp?stp=dst-jpg_e35&_nc_ht=scontent-iad3-2.cdninstagram.com&_nc_cat=111&_nc_ohc=Q76_HoQX87YAX_GTkZh&edm=APU89FABAAAA&ccb=7-5&ig_cache_key=MzA3NTM4MjUzMTM2OTU3NTgxMw%3D%3D.2-ccb7-5&oh=00_AfBo81BAu6PuO4uXE80VEDMwDxv6gK83M6kY1YnAVchsng&oe=64639899&_nc_sid=86f79a"},{"id":"3075297774912717612","pictures":"https://scontent-iad3-1.cdninstagram.com/v/t51.2885-15/339834453_934941544518985_3330649927278246850_n.webp?stp=dst-jpg_e35&_nc_ht=scontent-iad3-1.cdninstagram.com&_nc_cat=101&_nc_ohc=F2hT6Wc7LgMAX8FJrPl&edm=APU89FABAAAA&ccb=7-5&ig_cache_key=MzA3NTI5Nzc2ODc3MjMyNTc5Ng%3D%3D.2-ccb7-5&oh=00_AfCEZt0yO6WV9RCCWbPb2nOdQxdkR3voBz-a_DhmW8NHdA&oe=64635041&_nc_sid=86f79a"},{"id":"3075018546413760485","pictures":"https://scontent-iad3-2.cdninstagram.com/v/t51.2885-15/339821900_522642800076696_8084681536374856697_n.webp?stp=dst-jpg_e35&_nc_ht=scontent-iad3-2.cdninstagram.com&_nc_cat=100&_nc_ohc=zgT5XDqzxvIAX-mGRIx&edm=APU89FABAAAA&ccb=7-5&ig_cache_key=MzA3NTAxODU0NjQxMzc2MDQ4NQ%3D%3D.2-ccb7-5&oh=00_AfAIOft1x5ssvaOE2gE9JaRhSMPhlrbwShaEJkEMwnErvg&oe=6463F299&_nc_sid=86f79a"},{"id":"3074964611489587019","pictures":"https://scontent-iad3-1.cdninstagram.com/v/t51.2885-15/339505563_233484832568966_899114998125571576_n.webp?stp=dst-jpg_e35&_nc_ht=scontent-iad3-1.cdninstagram.com&_nc_cat=102&_nc_ohc=vPSIHXDOEJ4AX_6JybX&edm=APU89FABAAAA&ccb=7-5&ig_cache_key=MzA3NDk2NDYwNDcxMTU3OTU1MQ%3D%3D.2-ccb7-5&oh=00_AfDL7oML3H3xt-t4pLiedXVyjzyw7JjC5SSwMkG8dId8rQ&oe=64623E50&_nc_sid=86f79a"},{"id":"3074959940183978342","pictures":"https://scontent-iad3-1.cdninstagram.com/v/t51.2885-15/339525817_953161716030141_5648023181245364318_n.webp?stp=dst-jpg_e35&_nc_ht=scontent-iad3-1.cdninstagram.com&_nc_cat=109&_nc_ohc=i0XPTz9gF5sAX_jmjUU&edm=APU89FABAAAA&ccb=7-5&ig_cache_key=MzA3NDk1OTkzNTMxODU0ODU0Nw%3D%3D.2-ccb7-5&oh=00_AfD74G21x-xoJam7LJTcb5Z66zLgz0G46xXEAWC74xrJJg&oe=6463C89B&_nc_sid=86f79a"},{"id":"3074593285335506821","pictures":"https://scontent-iad3-2.cdninstagram.com/v/t51.2885-15/339505820_215136647792153_7864365099714335830_n.webp?stp=dst-jpg_e35&_nc_ht=scontent-iad3-2.cdninstagram.com&_nc_cat=105&_nc_ohc=NUYJUkzV-VgAX86wuEx&edm=APU89FABAAAA&ccb=7-5&ig_cache_key=MzA3NDU5MzI4NTMzNTUwNjgyMQ%3D%3D.2-ccb7-5&oh=00_AfCFa8N6XcGv3cJ-Wk0pVG0wgdNyyj5yfX2SXseVBuBD_w&oe=6463D223&_nc_sid=86f79a"},{"id":"3073663258217456366","pictures":"https://scontent-iad3-1.cdninstagram.com/v/t51.2885-15/339257453_633929098561975_1440269773218348440_n.webp?stp=dst-jpg_e35&_nc_ht=scontent-iad3-1.cdninstagram.com&_nc_cat=107&_nc_ohc=oC6_O5VzpeAAX-v4nhU&edm=APU89FABAAAA&ccb=7-5&ig_cache_key=MzA3MzY2MzI1NDA5ODY0MTc3MQ%3D%3D.2-ccb7-5&oh=00_AfBFIYasWMJuCMtP0wYW5Yp5wutuVdhjes6A9-66SML7ww&oe=6462685F&_nc_sid=86f79a"},{"id":"3073648444514585230","pictures":"https://scontent-iad3-2.cdninstagram.com/v/t51.2885-15/339193937_132231446343432_7303776077471591786_n.webp?stp=dst-jpg_e35&_nc_ht=scontent-iad3-2.cdninstagram.com&_nc_cat=100&_nc_ohc=GHG6tC4ameQAX9IDmm3&edm=APU89FABAAAA&ccb=7-5&ig_cache_key=MzA3MzY0ODQ0NDUxNDU4NTIzMA%3D%3D.2-ccb7-5&oh=00_AfBrILd9bFNPnOZO1_urrsr_0FuxwO2QIh2GQtsnIlMQIw&oe=64627151&_nc_sid=86f79a"},{"id":"3072971599209171702","pictures":"https://scontent-iad3-2.cdninstagram.com/v/t51.2885-15/339271606_238950131881218_776894393986149127_n.webp?stp=dst-jpg_e35&_nc_ht=scontent-iad3-2.cdninstagram.com&_nc_cat=106&_nc_ohc=f7NqIvAcHRIAX-TQuvX&edm=APU89FABAAAA&ccb=7-5&ig_cache_key=MzA3Mjk3MTU5NTkyOTI2NDc2MQ%3D%3D.2-ccb7-5&oh=00_AfAV4QkyevxKoYwbPsMkvlRFv78nt2LZNyC-aQcAV7NWtQ&oe=6462DC76&_nc_sid=86f79a"},{"id":"3072884293529809419","pictures":"https://scontent-iad3-1.cdninstagram.com/v/t51.2885-15/339176695_1283699065689974_2304530556211215868_n.webp?stp=dst-jpg_e35&_nc_ht=scontent-iad3-1.cdninstagram.com&_nc_cat=102&_nc_ohc=KrehcATPx2AAX_CC3Av&edm=APU89FABAAAA&ccb=7-5&ig_cache_key=MzA3Mjg4NDI5MzUyOTgwOTQxOQ%3D%3D.2-ccb7-5&oh=00_AfCHIIF2gSn2DTFQ-LaybHAkqpPL4iRjvW2mkwvsf_5sUg&oe=64637BE1&_nc_sid=86f79a"},{"id":"3072221975892591442","pictures":"https://scontent-iad3-1.cdninstagram.com/v/t51.2885-15/338919808_598432222206478_4511614737742437892_n.webp?stp=dst-jpg_e35&_nc_ht=scontent-iad3-1.cdninstagram.com&_nc_cat=110&_nc_ohc=mcOHXQPYs1oAX8d-Jmt&edm=APU89FABAAAA&ccb=7-5&ig_cache_key=MzA3MjIyMTk3MTY2NDYxOTU0MA%3D%3D.2-ccb7-5&oh=00_AfBAzi0moy_LYzTMImRg9cLzq1CtZ8-yu6X14MDE7qZbUQ&oe=646249D9&_nc_sid=86f79a"},{"id":"3072068273667846816","pictures":"https://scontent-iad3-2.cdninstagram.com/v/t51.2885-15/339302073_741536844181121_7624666358777683410_n.webp?stp=dst-jpg_e35&_nc_ht=scontent-iad3-2.cdninstagram.com&_nc_cat=105&_nc_ohc=CUAE_q0pR7oAX-r1Aij&edm=APU89FABAAAA&ccb=7-5&ig_cache_key=MzA3MjA2ODI3MzY2Nzg0NjgxNg%3D%3D.2-ccb7-5&oh=00_AfCfjbDmhUU_MyaajMKFJjeb5Y3e1nXuSkwVhx06gkvLRA&oe=646364DD&_nc_sid=86f79a"},{"id":"3069500938525013510","pictures":"https://scontent-iad3-2.cdninstagram.com/v/t51.2885-15/338552474_1252079335425270_2988910899646204244_n.jpg?stp=dst-jpg_e15&_nc_ht=scontent-iad3-2.cdninstagram.com&_nc_cat=106&_nc_ohc=Eqvt-dVnKA4AX8CgFWH&edm=APU89FABAAAA&ccb=7-5&oh=00_AfBfGyo3IpIT5Jmay-WYGcmQCvbRYjL56xlSAOgYC06bFg&oe=64601873&_nc_sid=86f79a","url":"https://scontent-iad3-2.cdninstagram.com/v/t66.30100-16/119810809_754594026215352_7327912061798722980_n.mp4?_nc_ht=scontent-iad3-2.cdninstagram.com&_nc_cat=100&_nc_ohc=Y_WTf42GsqAAX-KCdI_&edm=APU89FABAAAA&ccb=7-5&oh=00_AfCw6WTgvbOlcg8NKZO6Fed0SO5teuc1m4H7Oypy9R_qRw&oe=646019B6&_nc_sid=86f79a"},{"id":"3067988100093956346","pictures":"https://scontent-iad3-2.cdninstagram.com/v/t51.2885-15/337767679_883052919665526_3214909543111391378_n.webp?stp=dst-jpg_e35&_nc_ht=scontent-iad3-2.cdninstagram.com&_nc_cat=106&_nc_ohc=HfwLaO-WzroAX-1gtaD&edm=APU89FABAAAA&ccb=7-5&ig_cache_key=MzA2Nzk4ODEwMDA5Mzk1NjM0Ng%3D%3D.2-ccb7-5&oh=00_AfC5GrZkgLSt0x2x954T0uZJ7UZR-rU3BUGyV53y3QCa0A&oe=6462E505&_nc_sid=86f79a"},{"id":"3066630392463899589","pictures":"https://scontent-iad3-1.cdninstagram.com/v/t51.2885-15/337812959_1103682844357489_4102080056148281538_n.webp?stp=dst-jpg_e35&_nc_ht=scontent-iad3-1.cdninstagram.com&_nc_cat=101&_nc_ohc=5W1b1kNMMw4AX--aBCQ&edm=APU89FABAAAA&ccb=7-5&ig_cache_key=MzA2NjYzMDM5MjQ2Mzg5OTU4OQ%3D%3D.2-ccb7-5&oh=00_AfDO5F-b8v4t7PRlcOWavYwkeBpfQ8smG49-xtexGMY_og&oe=64629235&_nc_sid=86f79a"},{"id":"3066472402494500746","pictures":"https://scontent-iad3-1.cdninstagram.com/v/t51.2885-15/337423552_2330419917139197_6572500781410140474_n.webp?stp=dst-jpg_e35&_nc_ht=scontent-iad3-1.cdninstagram.com&_nc_cat=109&_nc_ohc=fEDebd1TAHMAX-qxitV&edm=APU89FABAAAA&ccb=7-5&ig_cache_key=MzA2NjQ3MjQwMjQ5NDUwMDc0Ng%3D%3D.2-ccb7-5&oh=00_AfAqVEhrnrmCDyrM8bHI1wetNqnQOz64XnapWq5cC7gxJQ&oe=6463CE46&_nc_sid=86f79a"},{"id":"2993432980526532356","pictures":"https://scontent-iad3-1.cdninstagram.com/v/t51.2885-15/320224622_710734100395844_5515632258656313210_n.webp?stp=dst-jpg_e35&_nc_ht=scontent-iad3-1.cdninstagram.com&_nc_cat=108&_nc_ohc=DrprF-Kcf9EAX8HLtaD&edm=APU89FABAAAA&ccb=7-5&ig_cache_key=Mjk5MzQzMjk4MDUyNjUzMjM1Ng%3D%3D.2-ccb7-5&oh=00_AfAPb-soCLm7dIxOTtTE2uQVBfIpVr0G_y2IO2WBVQRRuQ&oe=6462FCD9&_nc_sid=86f79a"},{"id":"2992400813675606642","pictures":"https://scontent-iad3-1.cdninstagram.com/v/t51.2885-15/319675205_3341252622856462_765181855059548513_n.webp?stp=dst-jpg_e35&_nc_ht=scontent-iad3-1.cdninstagram.com&_nc_cat=110&_nc_ohc=SHGKVbSUCwgAX_1SOUN&edm=APU89FABAAAA&ccb=7-5&ig_cache_key=Mjk5MjQwMDgxMzY3NTYwNjY0Mg%3D%3D.2-ccb7-5&oh=00_AfAe47GSbSuwDV7ke7YhwIfRHvQtROjnitc_LA7B3Lafaw&oe=64629614&_nc_sid=86f79a"},{"id":"2991717704588300370","pictures":"https://scontent-iad3-1.cdninstagram.com/v/t51.2885-15/319378925_1086440145350179_4752663468312493941_n.webp?stp=dst-jpg_e35&_nc_ht=scontent-iad3-1.cdninstagram.com&_nc_cat=107&_nc_ohc=nCyhozxZxBMAX_tCZmT&edm=APU89FABAAAA&ccb=7-5&ig_cache_key=Mjk5MTcxNzcwNDU4ODMwMDM3MA%3D%3D.2-ccb7-5&oh=00_AfDwtMfn2kp94THKWYcK02u18LXnjNRuXIenfbPgU5p6oA&oe=6462C483&_nc_sid=86f79a"},{"id":"2986215307621716618","pictures":"https://scontent-iad3-1.cdninstagram.com/v/t51.2885-15/318032135_901216601256152_6853408645758708467_n.webp?stp=dst-jpg_e35&_nc_ht=scontent-iad3-1.cdninstagram.com&_nc_cat=108&_nc_ohc=r871lJjaWDYAX-VLpmy&edm=APU89FABAAAA&ccb=7-5&ig_cache_key=Mjk4NjIxNTMwNzYyMTcxNjYxOA%3D%3D.2-ccb7-5&oh=00_AfDyBa56i6ZIdT-w3a8E44oOyKiTAlW_AdFHIaKq7-Anvw&oe=64626378&_nc_sid=86f79a"},{"id":"2981064944977122208","pictures":"https://scontent-iad3-1.cdninstagram.com/v/t51.2885-15/317002663_1563023654147731_2764756483622531415_n.webp?stp=dst-jpg_e35&_nc_ht=scontent-iad3-1.cdninstagram.com&_nc_cat=107&_nc_ohc=cFsAc1P37sgAX-_Q2o5&edm=APU89FABAAAA&ccb=7-5&ig_cache_key=Mjk4MTA2NDk0NDk3NzEyMjIwOA%3D%3D.2-ccb7-5&oh=00_AfBpZkX18vqeqFR8sPNaWvS4k1dbAhRO8NmhUbKokfnXgw&oe=64624A19&_nc_sid=86f79a"},{"id":"2981059754450277686","pictures":"https://scontent-iad3-1.cdninstagram.com/v/t51.2885-15/317036402_540724274222326_3339727233862086765_n.webp?stp=dst-jpg_e35&_nc_ht=scontent-iad3-1.cdninstagram.com&_nc_cat=110&_nc_ohc=PiOyXn54cRwAX8oErwD&edm=APU89FABAAAA&ccb=7-5&ig_cache_key=Mjk4MTA1OTc1NDQ1MDI3NzY4Ng%3D%3D.2-ccb7-5&oh=00_AfDMACA8_bFTovQAQPS1ldVIFHdpjjY1jX_tYGBc_korLg&oe=646370AA&_nc_sid=86f79a"},{"id":"2981054292812228643","pictures":"https://scontent-iad3-1.cdninstagram.com/v/t51.2885-15/316996530_469049932019410_5999219972784465151_n.webp?stp=dst-jpg_e35&_nc_ht=scontent-iad3-1.cdninstagram.com&_nc_cat=110&_nc_ohc=SbAS3AUFj7wAX9zyUAK&edm=APU89FABAAAA&ccb=7-5&ig_cache_key=Mjk4MTA1NDI5MjgxMjIyODY0Mw%3D%3D.2-ccb7-5&oh=00_AfAEBnNXOkl50crvnxCxAggfHhA1kFpz0lCcdiw9-MaPCg&oe=6463E825&_nc_sid=86f79a"},{"id":"2980345407621257285","pictures":"https://scontent-iad3-2.cdninstagram.com/v/t51.2885-15/317252391_1909916749359816_7302995916799065627_n.webp?stp=dst-jpg_e35&_nc_ht=scontent-iad3-2.cdninstagram.com&_nc_cat=100&_nc_ohc=hVq2oItx47IAX9SEyxJ&edm=APU89FABAAAA&ccb=7-5&ig_cache_key=Mjk4MDM0NTQwMjE4NTM5Njg2Nw%3D%3D.2-ccb7-5&oh=00_AfCgSKoNpKJR_Kyu9Prh6QseuV9Vwjx3nA83AuJSBTR6xQ&oe=6463A2B6&_nc_sid=86f79a"},{"id":"2975799019365222840","pictures":"https://scontent-iad3-1.cdninstagram.com/v/t51.2885-15/316055777_631776628690569_7236630237544898924_n.webp?stp=dst-jpg_e35&_nc_ht=scontent-iad3-1.cdninstagram.com&_nc_cat=109&_nc_ohc=dAoQT6IQxT4AX-mOAjJ&edm=APU89FABAAAA&ccb=7-5&ig_cache_key=Mjk3NTc5OTAxOTM2NTIyMjg0MA%3D%3D.2-ccb7-5&oh=00_AfBro_ujrQLeZ4wjGuPZT8J88cjTszV8hQyEd2DL06t2zA&oe=6464050B&_nc_sid=86f79a"},{"id":"2975785406692857864","pictures":"https://scontent-iad3-2.cdninstagram.com/v/t51.2885-15/316021832_129508463053740_639877365930182_n.webp?stp=dst-jpg_e35&_nc_ht=scontent-iad3-2.cdninstagram.com&_nc_cat=100&_nc_ohc=P-c4efnSseAAX-BApnM&edm=APU89FABAAAA&ccb=7-5&ig_cache_key=Mjk3NTc4NTQwMjU5MDg3ODIxMQ%3D%3D.2-ccb7-5&oh=00_AfAbsc8tdK61TlDZfqZdcs5WtvunPj7hPRUq-Add13-FxQ&oe=6462348F&_nc_sid=86f79a"},{"id":"2957697674292765576","pictures":"https://scontent-iad3-1.cdninstagram.com/v/t51.2885-15/312624199_8874133589278754_523232895009530656_n.webp?stp=dst-jpg_e35&_nc_ht=scontent-iad3-1.cdninstagram.com&_nc_cat=102&_nc_ohc=ansKC0a5QsUAX9HrNoM&edm=APU89FABAAAA&ccb=7-5&ig_cache_key=Mjk1NzY5NzY3NDI5Mjc2NTU3Ng%3D%3D.2-ccb7-5&oh=00_AfBUWxvSRsyhNoZljNn32Ai-9mErJ0hT70KZC4OVGn1zuQ&oe=64641B8D&_nc_sid=86f79a"},{"id":"2956476663180919046","pictures":"https://scontent-iad3-2.cdninstagram.com/v/t51.2885-15/313013798_893548408486134_1579138078497339589_n.webp?stp=dst-jpg_e35&_nc_ht=scontent-iad3-2.cdninstagram.com&_nc_cat=106&_nc_ohc=gapW-fjbdiEAX-TfAmH&edm=APU89FABAAAA&ccb=7-5&ig_cache_key=Mjk1NjQ3NjY2MzE4MDkxOTA0Ng%3D%3D.2-ccb7-5&oh=00_AfDnGFpLFykRmcqV27J_GBVLXXXJJOKXovMrr6-yozr4Kw&oe=64639525&_nc_sid=86f79a"},{"id":"2956383132258560141","pictures":"https://scontent-iad3-2.cdninstagram.com/v/t51.2885-15/312563141_1175573806368939_4322209642783483872_n.webp?stp=dst-jpg_e35&_nc_ht=scontent-iad3-2.cdninstagram.com&_nc_cat=103&_nc_ohc=sWEqjU2GmdAAX8CtRZP&edm=APU89FABAAAA&ccb=7-5&ig_cache_key=Mjk1NjM4MzEzMjI1ODU2MDE0MQ%3D%3D.2-ccb7-5&oh=00_AfANUsfK4MzHrj70PYanfdg6espBafs8f4tPxG9tUeHzdg&oe=646310DA&_nc_sid=86f79a"},{"id":"2955636568284315328","pictures":"https://scontent-iad3-1.cdninstagram.com/v/t51.2885-15/312498990_1160027631262870_2815835331040415886_n.webp?stp=dst-jpg_e35&_nc_ht=scontent-iad3-1.cdninstagram.com&_nc_cat=110&_nc_ohc=FuqvJF7BSUkAX8DIsSv&edm=APU89FABAAAA&ccb=7-5&ig_cache_key=Mjk1NTYzNjU2MzUxMTA4NzM4Mw%3D%3D.2-ccb7-5&oh=00_AfC2_YAIISBwh1F2SIfCO9sC8ca_jWw8V7tGwzqIFZCWiQ&oe=64624C48&_nc_sid=86f79a"},{"id":"2955632976266423426","pictures":"https://scontent-iad3-1.cdninstagram.com/v/t51.2885-15/312434048_207051141713349_6714767906822254980_n.webp?stp=dst-jpg_e35&_nc_ht=scontent-iad3-1.cdninstagram.com&_nc_cat=109&_nc_ohc=fzQ-AlURT6sAX-vOfGj&edm=APU89FABAAAA&ccb=7-5&ig_cache_key=Mjk1NTYzMjk3NjI2NjQyMzQyNg%3D%3D.2-ccb7-5&oh=00_AfDfJZ6Hr2ykzVh0YrS4TENw_tZX1NJQqNh_g5gLDgsCCA&oe=6462AAE8&_nc_sid=86f79a"},{"id":"2955631388000936157","pictures":"https://scontent-iad3-1.cdninstagram.com/v/t51.2885-15/312146339_784141899320458_3653713419055509545_n.webp?stp=dst-jpg_e35&_nc_ht=scontent-iad3-1.cdninstagram.com&_nc_cat=110&_nc_ohc=7EOXOG0FEGIAX9Xfhzu&edm=APU89FABAAAA&ccb=7-5&ig_cache_key=Mjk1NTYzMTM4MzcwNTg0NDk1MQ%3D%3D.2-ccb7-5&oh=00_AfAVeDaWVebGXuUEBIFqMN9AAFHf8fitBFWQGlXtovB1Kg&oe=64632FF3&_nc_sid=86f79a"},{"id":"2955562042976221512","pictures":"https://scontent-iad3-1.cdninstagram.com/v/t51.2885-15/312431211_188413447091612_5641848404828775874_n.webp?stp=dst-jpg_e35&_nc_ht=scontent-iad3-1.cdninstagram.com&_nc_cat=108&_nc_ohc=_2tCV0r7GosAX9C7O7j&edm=APU89FABAAAA&ccb=7-5&ig_cache_key=Mjk1NTU2MjAzODMyMDU1MzcwNg%3D%3D.2-ccb7-5&oh=00_AfC1r5Ghd_qsEFmuERwZ_O2SOw-5vshVDhafmZoTBhb1kw&oe=64624720&_nc_sid=86f79a"},{"id":"2955560391125155044","pictures":"https://scontent-iad3-1.cdninstagram.com/v/t51.2885-15/312470744_903848123933572_2217213726367316729_n.webp?stp=dst-jpg_e35&_nc_ht=scontent-iad3-1.cdninstagram.com&_nc_cat=104&_nc_ohc=ulMyU1aJ7hcAX_O7nzn&edm=APU89FABAAAA&ccb=7-5&ig_cache_key=Mjk1NTU2MDM4NjQ5NDYyMTMwMg%3D%3D.2-ccb7-5&oh=00_AfB5KGOTOtub9o_jOr-VsnL53IHMMoN_uQvrJckEGskoHg&oe=64624617&_nc_sid=86f79a"},{"id":"2955558118399507789","pictures":"https://scontent-iad3-2.cdninstagram.com/v/t51.2885-15/312387641_5439158246213850_6490213931569138585_n.webp?stp=dst-jpg_e35&_nc_ht=scontent-iad3-2.cdninstagram.com&_nc_cat=106&_nc_ohc=8nR8VVYYt2oAX_U753T&edm=APU89FABAAAA&ccb=7-5&ig_cache_key=Mjk1NTU1ODExNDA5NjE4Njc1Mw%3D%3D.2-ccb7-5&oh=00_AfBJf5elG81EOhS80OaJeNMQNdnQEGU7Erkizhxk6-HeVQ&oe=6463E226&_nc_sid=86f79a"},{"id":"2947583823832525156","pictures":"https://scontent-iad3-1.cdninstagram.com/v/t51.2885-15/311173256_8417209341652624_3000575915030618118_n.webp?stp=dst-jpg_e35&_nc_ht=scontent-iad3-1.cdninstagram.com&_nc_cat=104&_nc_ohc=uJAeh1Fp-ecAX8fHKGj&edm=APU89FABAAAA&ccb=7-5&ig_cache_key=Mjk0NzU4MzgyMzgzMjUyNTE1Ng%3D%3D.2-ccb7-5&oh=00_AfAkdarHOPzRGxvaKsT9uA01kQdZ-BLdWai2nhqX9Jf3YQ&oe=6463272E&_nc_sid=86f79a"}]