[{"id":"3095522940133717260","pictures":"https://scontent-iad3-2.cdninstagram.com/v/t51.2885-15/344578632_528603772608939_6702985190009468156_n.webp?stp=dst-jpg_e35&_nc_ht=scontent-iad3-2.cdninstagram.com&_nc_cat=103&_nc_ohc=mPQUbk0VBl0AX90uVvA&edm=APU89FABAAAA&ccb=7-5&ig_cache_key=MzA5NTUyMjkzNDIzNjQ0ODE3Ng%3D%3D.2-ccb7-5&oh=00_AfBqlnj32qSdsn9U0YoJQZomNPXlhQWwUCHO0o4Y8jNaSA&oe=645B1B96&_nc_sid=86f79a"},{"id":"3094709379895181480","pictures":"https://scontent-iad3-2.cdninstagram.com/v/t51.2885-15/345025867_1585784225243871_2733132503802474760_n.webp?stp=dst-jpg_e35&_nc_ht=scontent-iad3-2.cdninstagram.com&_nc_cat=103&_nc_ohc=nSZC9MIbXsQAX-PIQ3W&edm=APU89FABAAAA&ccb=7-5&ig_cache_key=MzA5NDcwOTM3OTg5NTE4MTQ4MA%3D%3D.2-ccb7-5&oh=00_AfBljEYyTkyRJYWkRaULDRgFnJiDldtJu21bQ3p8v-vaGQ&oe=645B76AC&_nc_sid=86f79a"},{"id":"3093284618245803580","pictures":"https://scontent-iad3-2.cdninstagram.com/v/t51.2885-15/344553948_197740969739472_6876540254203201706_n.webp?stp=dst-jpg_e35&_nc_ht=scontent-iad3-2.cdninstagram.com&_nc_cat=100&_nc_ohc=zQQeI1nkwvkAX8Ulr1T&edm=APU89FABAAAA&ccb=7-5&ig_cache_key=MzA5MzI4NDYxODI0NTgwMzU4MA%3D%3D.2-ccb7-5&oh=00_AfDqYWbYgwWGKIy0E2C07AIw7eRULZQ4LW7wXRrIn3MM8Q&oe=645A6AD1&_nc_sid=86f79a"},{"id":"3093138830253534367","pictures":"https://scontent-iad3-1.cdninstagram.com/v/t51.2885-15/344173677_792101979112114_5062795211153346023_n.webp?stp=dst-jpg_e35&_nc_ht=scontent-iad3-1.cdninstagram.com&_nc_cat=110&_nc_ohc=llDoJBnQ2IIAX-5BXjO&edm=APU89FABAAAA&ccb=7-5&ig_cache_key=MzA5MzEzODgzMDI1MzUzNDM2Nw%3D%3D.2-ccb7-5&oh=00_AfALGoiKr3CSJlDIeedf9RrrJtxVVJff_s6tovZpnOpFCw&oe=645B4668&_nc_sid=86f79a"},{"id":"3082344423031883874","pictures":"https://scontent-iad3-1.cdninstagram.com/v/t51.2885-15/328341117_947158293380510_5348614167709273928_n.webp?stp=dst-jpg_e35&_nc_ht=scontent-iad3-1.cdninstagram.com&_nc_cat=102&_nc_ohc=TmFhZf2HRuwAX_4UsKe&edm=APU89FABAAAA&ccb=7-5&ig_cache_key=MzA4MjM0NDQxNzUwMzc3NjkzMA%3D%3D.2-ccb7-5&oh=00_AfBeGuM7if9KkQwbxFVPTFYjXa2NSzaWpuawOlpUpQGu-g&oe=645A165B&_nc_sid=86f79a"},{"id":"3082236523127090054","pictures":"https://scontent-iad3-1.cdninstagram.com/v/t51.2885-15/341586044_533688895593571_2970840009187163550_n.webp?stp=dst-jpg_e35&_nc_ht=scontent-iad3-1.cdninstagram.com&_nc_cat=107&_nc_ohc=Kb_yfS8SM2oAX8R8m6I&edm=APU89FABAAAA&ccb=7-5&ig_cache_key=MzA4MjIzNjUyMzEyNzA5MDA1NA%3D%3D.2-ccb7-5&oh=00_AfA8nXOhyE-bqmDP-eoW6DUs547S15cqhmLxIxp0T_LX2g&oe=645B8751&_nc_sid=86f79a"},{"id":"3077412803673933050","pictures":"https://scontent-iad3-2.cdninstagram.com/v/t51.2885-15/340160248_1334235187432763_1095476699837930138_n.webp?stp=dst-jpg_e35&_nc_ht=scontent-iad3-2.cdninstagram.com&_nc_cat=111&_nc_ohc=3l3wN5asFJEAX9ElJW8&edm=APU89FABAAAA&ccb=7-5&ig_cache_key=MzA3NzQxMjgwMzY3MzkzMzA1MA%3D%3D.2-ccb7-5&oh=00_AfBHIWiQBdZYRGKByOa12eEuDQ6IGYt6qn6H7i8VBL_efQ&oe=645B19D0&_nc_sid=86f79a"},{"id":"3077405593120094821","pictures":"https://scontent-iad3-1.cdninstagram.com/v/t51.2885-15/340175130_572728651501718_7861409328666524617_n.webp?stp=dst-jpg_e35&_nc_ht=scontent-iad3-1.cdninstagram.com&_nc_cat=102&_nc_ohc=wg4AUm-raVwAX_qp1sC&edm=APU89FABAAAA&ccb=7-5&ig_cache_key=MzA3NzQwNTU5MzEyMDA5NDgyMQ%3D%3D.2-ccb7-5&oh=00_AfA2GF2HLr6e-bTTJyI57px1biNlKGSXlstB3RN2UxTVLw&oe=645A1C68&_nc_sid=86f79a"},{"id":"3077398913380644988","pictures":"https://scontent-iad3-1.cdninstagram.com/v/t51.2885-15/340653832_263826449319896_1165135371871733392_n.webp?stp=dst-jpg_e35&_nc_ht=scontent-iad3-1.cdninstagram.com&_nc_cat=108&_nc_ohc=D-6eSnhgg4oAX-pLPYG&edm=APU89FABAAAA&ccb=7-5&ig_cache_key=MzA3NzM5ODkxMzM4MDY0NDk4OA%3D%3D.2-ccb7-5&oh=00_AfAAQg2SrXWsHkEUAIh4ghq3ldca0f6LiOQ-HwtkwQP5DA&oe=645B3562&_nc_sid=86f79a"},{"id":"3077183728556567257","pictures":"https://scontent-iad3-2.cdninstagram.com/v/t51.2885-15/340178038_926939471905686_1386896573733632857_n.jpg?stp=dst-jpg_e15&_nc_ht=scontent-iad3-2.cdninstagram.com&_nc_cat=106&_nc_ohc=K41MKFZZuhIAX80A6Zq&edm=APU89FABAAAA&ccb=7-5&oh=00_AfAjcl7E39XUqLIOBQiQFE8Q_LVXyavNAibZI4gmG8i2MA&oe=6457727D&_nc_sid=86f79a"},{"id":"3076620312800643143","pictures":"https://scontent-iad3-1.cdninstagram.com/v/t51.2885-15/340334429_945527096633402_2251344375844282067_n.webp?stp=dst-jpg_e35&_nc_ht=scontent-iad3-1.cdninstagram.com&_nc_cat=102&_nc_ohc=1Mx0l1EawHcAX9l5Z0P&edm=APU89FABAAAA&ccb=7-5&ig_cache_key=MzA3NjYyMDMxMjgwMDY0MzE0Mw%3D%3D.2-ccb7-5&oh=00_AfAymBNRKmBFLJWGcnOa1AaSAXT4rTZp5GITdEeTfCbRXw&oe=645AE04B&_nc_sid=86f79a"},{"id":"3076039130694214531","pictures":"https://scontent-iad3-1.cdninstagram.com/v/t51.2885-15/339829528_1163641847662606_7723495676839436787_n.webp?stp=dst-jpg_e35&_nc_ht=scontent-iad3-1.cdninstagram.com&_nc_cat=110&_nc_ohc=1ixEpR2hsgMAX-oc9aN&edm=APU89FABAAAA&ccb=7-5&ig_cache_key=MzA3NjAzOTEyNDQ3ODI0MTUzMg%3D%3D.2-ccb7-5&oh=00_AfA_cjm4ujVIM9WNAPA8xzZnP3buW34NwVrbAzx3zpZqxg&oe=6459E37F&_nc_sid=86f79a"},{"id":"3076023385016983734","pictures":"https://scontent-iad3-2.cdninstagram.com/v/t51.2885-15/339998326_762589435468451_7355595665232484760_n.webp?stp=dst-jpg_e35&_nc_ht=scontent-iad3-2.cdninstagram.com&_nc_cat=111&_nc_ohc=Ml0jgKFqHucAX8gAwQE&edm=APU89FABAAAA&ccb=7-5&ig_cache_key=MzA3NjAyMzM3ODIzMDM3OTU2Mw%3D%3D.2-ccb7-5&oh=00_AfBiriHZMoDIAKG6cGbolxUM7ZdiaiJDk4BriDw-9Y8zow&oe=6459C98E&_nc_sid=86f79a"},{"id":"3075665891576973368","pictures":"https://scontent-iad3-1.cdninstagram.com/v/t51.2885-15/339865729_930835888042243_7441994661172486693_n.webp?stp=dst-jpg_e35&_nc_ht=scontent-iad3-1.cdninstagram.com&_nc_cat=107&_nc_ohc=MkQik8cSoa4AX9ctUmS&edm=APU89FABAAAA&ccb=7-5&ig_cache_key=MzA3NTY2NTg5MTU3Njk3MzM2OA%3D%3D.2-ccb7-5&oh=00_AfA1vhLqZfSNLu08BT_1A5iAkf8r3apdzYnF63EQY45O5w&oe=645B7024&_nc_sid=86f79a"},{"id":"3075382536083986280","pictures":"https://scontent-iad3-2.cdninstagram.com/v/t51.2885-15/339674169_236374522210847_964000247987090615_n.webp?stp=dst-jpg_e35&_nc_ht=scontent-iad3-2.cdninstagram.com&_nc_cat=111&_nc_ohc=BRtXGnIUfgAAX8inGxZ&edm=APU89FABAAAA&ccb=7-5&ig_cache_key=MzA3NTM4MjUzMTM2OTU3NTgxMw%3D%3D.2-ccb7-5&oh=00_AfDV9VoBoczlARi3AENSQgV1mnRE-2wQ-c6WKYoBzUsbSw&oe=6459B559&_nc_sid=86f79a"},{"id":"3075297774912717612","pictures":"https://scontent-iad3-1.cdninstagram.com/v/t51.2885-15/339834453_934941544518985_3330649927278246850_n.webp?stp=dst-jpg_e35&_nc_ht=scontent-iad3-1.cdninstagram.com&_nc_cat=101&_nc_ohc=2b3SGtidXTsAX87QboC&edm=APU89FABAAAA&ccb=7-5&ig_cache_key=MzA3NTI5Nzc2ODc3MjMyNTc5Ng%3D%3D.2-ccb7-5&oh=00_AfBERSKkW-g8RH0iDyMhLAZ1e86SYD25EVf2W475wYa4Yw&oe=645B6741&_nc_sid=86f79a"},{"id":"3075018546413760485","pictures":"https://scontent-iad3-2.cdninstagram.com/v/t51.2885-15/339821900_522642800076696_8084681536374856697_n.webp?stp=dst-jpg_e35&_nc_ht=scontent-iad3-2.cdninstagram.com&_nc_cat=100&_nc_ohc=v6zynmxwJSMAX9Z55mR&edm=APU89FABAAAA&ccb=7-5&ig_cache_key=MzA3NTAxODU0NjQxMzc2MDQ4NQ%3D%3D.2-ccb7-5&oh=00_AfC5VAAfG5eNid5HuAHNiRNCLC3D2o7IpLpE5zokfzgWhw&oe=645A0F59&_nc_sid=86f79a"},{"id":"3074964611489587019","pictures":"https://scontent-iad3-1.cdninstagram.com/v/t51.2885-15/339505563_233484832568966_899114998125571576_n.webp?stp=dst-jpg_e35&_nc_ht=scontent-iad3-1.cdninstagram.com&_nc_cat=102&_nc_ohc=Bb4N1gewWSUAX8TIrro&edm=APU89FABAAAA&ccb=7-5&ig_cache_key=MzA3NDk2NDYwNDcxMTU3OTU1MQ%3D%3D.2-ccb7-5&oh=00_AfAd9MAL5MBNH6BCVKJGRpR7HgFDO7Zg59gC66Fu1ELy2A&oe=645A5550&_nc_sid=86f79a"},{"id":"3074959940183978342","pictures":"https://scontent-iad3-1.cdninstagram.com/v/t51.2885-15/339525817_953161716030141_5648023181245364318_n.webp?stp=dst-jpg_e35&_nc_ht=scontent-iad3-1.cdninstagram.com&_nc_cat=109&_nc_ohc=j_hHIhRK3dwAX8V6orW&edm=APU89FABAAAA&ccb=7-5&ig_cache_key=MzA3NDk1OTkzNTMxODU0ODU0Nw%3D%3D.2-ccb7-5&oh=00_AfABLuO9qJUApYBsChSETVlxyaulZCwWnI8eY9tIOv22Qw&oe=6459E55B&_nc_sid=86f79a"},{"id":"3074593285335506821","pictures":"https://scontent-iad3-2.cdninstagram.com/v/t51.2885-15/339505820_215136647792153_7864365099714335830_n.webp?stp=dst-jpg_e35&_nc_ht=scontent-iad3-2.cdninstagram.com&_nc_cat=105&_nc_ohc=o9WYkWeUC9wAX_2dzAP&edm=APU89FABAAAA&ccb=7-5&ig_cache_key=MzA3NDU5MzI4NTMzNTUwNjgyMQ%3D%3D.2-ccb7-5&oh=00_AfAHiWmH0zsg9GwuR2wHpYnpOG8WT875LhyOgW_fb_NNtg&oe=6459EEE3&_nc_sid=86f79a"},{"id":"3073663258217456366","pictures":"https://scontent-iad3-1.cdninstagram.com/v/t51.2885-15/339257453_633929098561975_1440269773218348440_n.webp?stp=dst-jpg_e35&_nc_ht=scontent-iad3-1.cdninstagram.com&_nc_cat=107&_nc_ohc=nWu5dDXr_MkAX9HpY1B&edm=APU89FABAAAA&ccb=7-5&ig_cache_key=MzA3MzY2MzI1NDA5ODY0MTc3MQ%3D%3D.2-ccb7-5&oh=00_AfA24GRvCbOvnwZ9vR0p2L04QLqKx-sVLzNyDqtUq--qgA&oe=645A7F5F&_nc_sid=86f79a"},{"id":"3073648444514585230","pictures":"https://scontent-iad3-2.cdninstagram.com/v/t51.2885-15/339193937_132231446343432_7303776077471591786_n.webp?stp=dst-jpg_e35&_nc_ht=scontent-iad3-2.cdninstagram.com&_nc_cat=100&_nc_ohc=yaJbbbAiPKAAX9l4qJ_&edm=APU89FABAAAA&ccb=7-5&ig_cache_key=MzA3MzY0ODQ0NDUxNDU4NTIzMA%3D%3D.2-ccb7-5&oh=00_AfDDuRVAQ6dcfbpqGrfmPnMWeGQSoyjUOfm0ADkKH6HXSw&oe=645A8851&_nc_sid=86f79a"},{"id":"3072971599209171702","pictures":"https://scontent-iad3-2.cdninstagram.com/v/t51.2885-15/339271606_238950131881218_776894393986149127_n.webp?stp=dst-jpg_e35&_nc_ht=scontent-iad3-2.cdninstagram.com&_nc_cat=106&_nc_ohc=5HQ2cpmbQQMAX-4a159&edm=APU89FABAAAA&ccb=7-5&ig_cache_key=MzA3Mjk3MTU5NTkyOTI2NDc2MQ%3D%3D.2-ccb7-5&oh=00_AfBPGdZ2F8dwCbF4rS9obStIw3xWQ3FCKO4BnY8Uadzn9g&oe=645AF376&_nc_sid=86f79a"},{"id":"3072884293529809419","pictures":"https://scontent-iad3-1.cdninstagram.com/v/t51.2885-15/339176695_1283699065689974_2304530556211215868_n.webp?stp=dst-jpg_e35&_nc_ht=scontent-iad3-1.cdninstagram.com&_nc_cat=102&_nc_ohc=Q1a9lHe2inQAX_KqO0F&edm=APU89FABAAAA&ccb=7-5&ig_cache_key=MzA3Mjg4NDI5MzUyOTgwOTQxOQ%3D%3D.2-ccb7-5&oh=00_AfBoZ8_CneeW8C-o0r6hKlYamokkSKlqReXMbv5cMUOKLQ&oe=645998A1&_nc_sid=86f79a"},{"id":"3072221975892591442","pictures":"https://scontent-iad3-1.cdninstagram.com/v/t51.2885-15/338919808_598432222206478_4511614737742437892_n.webp?stp=dst-jpg_e35&_nc_ht=scontent-iad3-1.cdninstagram.com&_nc_cat=110&_nc_ohc=HFd9FJBFyP8AX-jdN_L&edm=APU89FABAAAA&ccb=7-5&ig_cache_key=MzA3MjIyMTk3MTY2NDYxOTU0MA%3D%3D.2-ccb7-5&oh=00_AfAqr_HzS26qoyyrryNtmcD0YYGVwLL1wLU0jBWOqW0cUg&oe=645A60D9&_nc_sid=86f79a"},{"id":"3072068273667846816","pictures":"https://scontent-iad3-2.cdninstagram.com/v/t51.2885-15/339302073_741536844181121_7624666358777683410_n.webp?stp=dst-jpg_e35&_nc_ht=scontent-iad3-2.cdninstagram.com&_nc_cat=105&_nc_ohc=UCmk8sFIZN4AX-qi0O6&edm=APU89FABAAAA&ccb=7-5&ig_cache_key=MzA3MjA2ODI3MzY2Nzg0NjgxNg%3D%3D.2-ccb7-5&oh=00_AfCMthC_JZM-ZFheW4HTKr0PMYlTdRo5zI--ZRizEUl3lQ&oe=645B7BDD&_nc_sid=86f79a"},{"id":"3069500938525013510","pictures":"https://scontent-iad3-2.cdninstagram.com/v/t51.2885-15/338552474_1252079335425270_2988910899646204244_n.jpg?stp=dst-jpg_e15&_nc_ht=scontent-iad3-2.cdninstagram.com&_nc_cat=106&_nc_ohc=DqHri9AzQ2cAX99n3H-&edm=APU89FABAAAA&ccb=7-5&oh=00_AfCXS3BgSfMwTDbkEaJcgXkMdom-PFAUhNnnnlioks8zww&oe=645786B3&_nc_sid=86f79a","url":"https://scontent-iad3-2.cdninstagram.com/v/t66.30100-16/119810809_754594026215352_7327912061798722980_n.mp4?_nc_ht=scontent-iad3-2.cdninstagram.com&_nc_cat=100&_nc_ohc=iPgF8HosAj8AX8xo-bO&edm=APU89FABAAAA&ccb=7-5&oh=00_AfARtbrmtWT6Zf1cNI_FSPlF1VtZ4PK6nerb2cr5CINg7Q&oe=645787F6&_nc_sid=86f79a"},{"id":"3067988100093956346","pictures":"https://scontent-iad3-2.cdninstagram.com/v/t51.2885-15/337767679_883052919665526_3214909543111391378_n.webp?stp=dst-jpg_e35&_nc_ht=scontent-iad3-2.cdninstagram.com&_nc_cat=106&_nc_ohc=_LSXC7xNj6wAX9CNvrq&edm=APU89FABAAAA&ccb=7-5&ig_cache_key=MzA2Nzk4ODEwMDA5Mzk1NjM0Ng%3D%3D.2-ccb7-5&oh=00_AfBw0jokGRhoNXIOl2Bg-e6ZyFFldTfJFekmgeQzP9_ipw&oe=645AFC05&_nc_sid=86f79a"},{"id":"3066630392463899589","pictures":"https://scontent-iad3-1.cdninstagram.com/v/t51.2885-15/337812959_1103682844357489_4102080056148281538_n.webp?stp=dst-jpg_e35&_nc_ht=scontent-iad3-1.cdninstagram.com&_nc_cat=101&_nc_ohc=kp3bt9rRe2oAX8o3coQ&edm=APU89FABAAAA&ccb=7-5&ig_cache_key=MzA2NjYzMDM5MjQ2Mzg5OTU4OQ%3D%3D.2-ccb7-5&oh=00_AfDV3jXEElMM3GBwmpVI06_eJopsBGzQ-TtgnNra3IiQ_Q&oe=645AA935&_nc_sid=86f79a"},{"id":"3066472402494500746","pictures":"https://scontent-iad3-1.cdninstagram.com/v/t51.2885-15/337423552_2330419917139197_6572500781410140474_n.webp?stp=dst-jpg_e35&_nc_ht=scontent-iad3-1.cdninstagram.com&_nc_cat=109&_nc_ohc=ccWuAYyesi4AX8nvOEF&edm=APU89FABAAAA&ccb=7-5&ig_cache_key=MzA2NjQ3MjQwMjQ5NDUwMDc0Ng%3D%3D.2-ccb7-5&oh=00_AfAXwRgWbA7Pu6D1s1kpOUatQZow2kHCWBR7YRvl17OHlw&oe=6459EB06&_nc_sid=86f79a"},{"id":"2993432980526532356","pictures":"https://scontent-iad3-1.cdninstagram.com/v/t51.2885-15/320224622_710734100395844_5515632258656313210_n.webp?stp=dst-jpg_e35&_nc_ht=scontent-iad3-1.cdninstagram.com&_nc_cat=108&_nc_ohc=kM19mc1e-poAX_PSk_h&edm=APU89FABAAAA&ccb=7-5&ig_cache_key=Mjk5MzQzMjk4MDUyNjUzMjM1Ng%3D%3D.2-ccb7-5&oh=00_AfAArmjcoqF3UwFCkIImITpZRS6gmv5uTkWV-q1SCk0xQQ&oe=645B13D9&_nc_sid=86f79a"},{"id":"2992400813675606642","pictures":"https://scontent-iad3-1.cdninstagram.com/v/t51.2885-15/319675205_3341252622856462_765181855059548513_n.webp?stp=dst-jpg_e35&_nc_ht=scontent-iad3-1.cdninstagram.com&_nc_cat=110&_nc_ohc=DAt4l_6v7_sAX8SQVFR&edm=APU89FABAAAA&ccb=7-5&ig_cache_key=Mjk5MjQwMDgxMzY3NTYwNjY0Mg%3D%3D.2-ccb7-5&oh=00_AfAA7Iu8u5EA38j1sSVLgW4rwU4xDS9wr7ZbUfejf78t5w&oe=645AAD14&_nc_sid=86f79a"},{"id":"2991717704588300370","pictures":"https://scontent-iad3-1.cdninstagram.com/v/t51.2885-15/319378925_1086440145350179_4752663468312493941_n.webp?stp=dst-jpg_e35&_nc_ht=scontent-iad3-1.cdninstagram.com&_nc_cat=107&_nc_ohc=5qC4tT4_hIkAX9fJjd7&edm=APU89FABAAAA&ccb=7-5&ig_cache_key=Mjk5MTcxNzcwNDU4ODMwMDM3MA%3D%3D.2-ccb7-5&oh=00_AfDhAcMmZO4Ms8hV-RCtMf8f8I3365i1g8HgdcyWVB3h2A&oe=645ADB83&_nc_sid=86f79a"},{"id":"2986215307621716618","pictures":"https://scontent-iad3-1.cdninstagram.com/v/t51.2885-15/318032135_901216601256152_6853408645758708467_n.webp?stp=dst-jpg_e35&_nc_ht=scontent-iad3-1.cdninstagram.com&_nc_cat=108&_nc_ohc=sxPI1_hWxHUAX_f0Ros&edm=APU89FABAAAA&ccb=7-5&ig_cache_key=Mjk4NjIxNTMwNzYyMTcxNjYxOA%3D%3D.2-ccb7-5&oh=00_AfAUu4ptWl9V_jK6_8_b10OyXezu9mohzWVEWttNt4mVyQ&oe=645A7A78&_nc_sid=86f79a"},{"id":"2981064944977122208","pictures":"https://scontent-iad3-1.cdninstagram.com/v/t51.2885-15/317002663_1563023654147731_2764756483622531415_n.webp?stp=dst-jpg_e35&_nc_ht=scontent-iad3-1.cdninstagram.com&_nc_cat=107&_nc_ohc=buhQi34PTwAAX-lGeOc&edm=APU89FABAAAA&ccb=7-5&ig_cache_key=Mjk4MTA2NDk0NDk3NzEyMjIwOA%3D%3D.2-ccb7-5&oh=00_AfCENdaFvrO4ou6nF9YSkfc3tVNwofCbGxYJuRrmexn6Iw&oe=645A6119&_nc_sid=86f79a"},{"id":"2981059754450277686","pictures":"https://scontent-iad3-1.cdninstagram.com/v/t51.2885-15/317036402_540724274222326_3339727233862086765_n.webp?stp=dst-jpg_e35&_nc_ht=scontent-iad3-1.cdninstagram.com&_nc_cat=110&_nc_ohc=P-WLeyqwYNoAX9iF3dG&edm=APU89FABAAAA&ccb=7-5&ig_cache_key=Mjk4MTA1OTc1NDQ1MDI3NzY4Ng%3D%3D.2-ccb7-5&oh=00_AfAQVXJUrhWn-9vp535HvaAgIDQhROW36xVrtFu0qtPylw&oe=645B87AA&_nc_sid=86f79a"},{"id":"2981054292812228643","pictures":"https://scontent-iad3-1.cdninstagram.com/v/t51.2885-15/316996530_469049932019410_5999219972784465151_n.webp?stp=dst-jpg_e35&_nc_ht=scontent-iad3-1.cdninstagram.com&_nc_cat=110&_nc_ohc=GHEkp1rW3xQAX8Ihz17&edm=APU89FABAAAA&ccb=7-5&ig_cache_key=Mjk4MTA1NDI5MjgxMjIyODY0Mw%3D%3D.2-ccb7-5&oh=00_AfDW2ZA9K-G3LrnK9FJSAsZvO6weSQFMSU_Lw56WTXZ3kA&oe=645A04E5&_nc_sid=86f79a"},{"id":"2980345407621257285","pictures":"https://scontent-iad3-2.cdninstagram.com/v/t51.2885-15/317252391_1909916749359816_7302995916799065627_n.webp?stp=dst-jpg_e35&_nc_ht=scontent-iad3-2.cdninstagram.com&_nc_cat=100&_nc_ohc=_YWwxJV9RQMAX9qrC6v&edm=APU89FABAAAA&ccb=7-5&ig_cache_key=Mjk4MDM0NTQwMjE4NTM5Njg2Nw%3D%3D.2-ccb7-5&oh=00_AfCYQ52NFZwK6gGikFrgMw_zR7rTsDg_8t6TWFy1R3UuVQ&oe=6459BF76&_nc_sid=86f79a"},{"id":"2975799019365222840","pictures":"https://scontent-iad3-1.cdninstagram.com/v/t51.2885-15/316055777_631776628690569_7236630237544898924_n.webp?stp=dst-jpg_e35&_nc_ht=scontent-iad3-1.cdninstagram.com&_nc_cat=109&_nc_ohc=JmicVQFPJ_MAX8rNZFQ&edm=APU89FABAAAA&ccb=7-5&ig_cache_key=Mjk3NTc5OTAxOTM2NTIyMjg0MA%3D%3D.2-ccb7-5&oh=00_AfD_SI39EV_bk-wMln3uzjkB35mfkOU-fv2fhsHoI7b5AA&oe=645A21CB&_nc_sid=86f79a"},{"id":"2975785406692857864","pictures":"https://scontent-iad3-2.cdninstagram.com/v/t51.2885-15/316021832_129508463053740_639877365930182_n.webp?stp=dst-jpg_e35&_nc_ht=scontent-iad3-2.cdninstagram.com&_nc_cat=100&_nc_ohc=GwCU-paP5tQAX99D9nt&edm=APU89FABAAAA&ccb=7-5&ig_cache_key=Mjk3NTc4NTQwMjU5MDg3ODIxMQ%3D%3D.2-ccb7-5&oh=00_AfAfFEPSGBgHFY-2ppeD7KBU-9S_5lYTRvDgiGOJ8uuJGQ&oe=645A4B8F&_nc_sid=86f79a"},{"id":"2957697674292765576","pictures":"https://scontent-iad3-1.cdninstagram.com/v/t51.2885-15/312624199_8874133589278754_523232895009530656_n.webp?stp=dst-jpg_e35&_nc_ht=scontent-iad3-1.cdninstagram.com&_nc_cat=102&_nc_ohc=b-hLYbeJvnAAX9PNCg0&edm=APU89FABAAAA&ccb=7-5&ig_cache_key=Mjk1NzY5NzY3NDI5Mjc2NTU3Ng%3D%3D.2-ccb7-5&oh=00_AfBiRSSMkeEt68Yp_Fu8GLNhHdOkp2m8kq_6hN8pVERzrg&oe=645A384D&_nc_sid=86f79a"},{"id":"2956476663180919046","pictures":"https://scontent-iad3-2.cdninstagram.com/v/t51.2885-15/313013798_893548408486134_1579138078497339589_n.webp?stp=dst-jpg_e35&_nc_ht=scontent-iad3-2.cdninstagram.com&_nc_cat=106&_nc_ohc=ooCwlt57hBQAX-aUsTP&edm=APU89FABAAAA&ccb=7-5&ig_cache_key=Mjk1NjQ3NjY2MzE4MDkxOTA0Ng%3D%3D.2-ccb7-5&oh=00_AfBHyApk6F-k4tzgf6ghV4gADjktsyZZj0kXvqVSU_18Kg&oe=6459B1E5&_nc_sid=86f79a"},{"id":"2956383132258560141","pictures":"https://scontent-iad3-2.cdninstagram.com/v/t51.2885-15/312563141_1175573806368939_4322209642783483872_n.webp?stp=dst-jpg_e35&_nc_ht=scontent-iad3-2.cdninstagram.com&_nc_cat=103&_nc_ohc=Qh13zd1KPAAAX-2pG-6&edm=APU89FABAAAA&ccb=7-5&ig_cache_key=Mjk1NjM4MzEzMjI1ODU2MDE0MQ%3D%3D.2-ccb7-5&oh=00_AfBJWuXxSXeQTWfQPfiXHnNEa8yPbBheRVsU_gwhpjsKhg&oe=645B27DA&_nc_sid=86f79a"},{"id":"2955636568284315328","pictures":"https://scontent-iad3-1.cdninstagram.com/v/t51.2885-15/312498990_1160027631262870_2815835331040415886_n.webp?stp=dst-jpg_e35&_nc_ht=scontent-iad3-1.cdninstagram.com&_nc_cat=110&_nc_ohc=8x1XBkhYe6oAX_pjST_&edm=APU89FABAAAA&ccb=7-5&ig_cache_key=Mjk1NTYzNjU2MzUxMTA4NzM4Mw%3D%3D.2-ccb7-5&oh=00_AfAQK1ez3NOPivzKhPy6nAB2Vl-WE_kzSFhAAiWO4krseg&oe=645A6348&_nc_sid=86f79a"},{"id":"2955632976266423426","pictures":"https://scontent-iad3-1.cdninstagram.com/v/t51.2885-15/312434048_207051141713349_6714767906822254980_n.webp?stp=dst-jpg_e35&_nc_ht=scontent-iad3-1.cdninstagram.com&_nc_cat=109&_nc_ohc=go70FH3Zx2IAX9tKKXj&edm=APU89FABAAAA&ccb=7-5&ig_cache_key=Mjk1NTYzMjk3NjI2NjQyMzQyNg%3D%3D.2-ccb7-5&oh=00_AfCWR4J-b7Bwuc6hLKRCIUJmzzZLxKAw89UG75pm8SzSXg&oe=645AC1E8&_nc_sid=86f79a"},{"id":"2955631388000936157","pictures":"https://scontent-iad3-1.cdninstagram.com/v/t51.2885-15/312146339_784141899320458_3653713419055509545_n.webp?stp=dst-jpg_e35&_nc_ht=scontent-iad3-1.cdninstagram.com&_nc_cat=110&_nc_ohc=T_DLoBDhocYAX_Hdwd3&edm=APU89FABAAAA&ccb=7-5&ig_cache_key=Mjk1NTYzMTM4MzcwNTg0NDk1MQ%3D%3D.2-ccb7-5&oh=00_AfCPZcAPNft8N4TlujSxueepwl0Qe9Dh6XxAhmq3ZOikCA&oe=645B46F3&_nc_sid=86f79a"},{"id":"2955562042976221512","pictures":"https://scontent-iad3-1.cdninstagram.com/v/t51.2885-15/312431211_188413447091612_5641848404828775874_n.webp?stp=dst-jpg_e35&_nc_ht=scontent-iad3-1.cdninstagram.com&_nc_cat=108&_nc_ohc=g51WocQX_iYAX9dAsPv&edm=APU89FABAAAA&ccb=7-5&ig_cache_key=Mjk1NTU2MjAzODMyMDU1MzcwNg%3D%3D.2-ccb7-5&oh=00_AfCuVJdlFuo3ww9f17_7xl5DBsroCIvaFnL8-Qtdf8399g&oe=645A5E20&_nc_sid=86f79a"},{"id":"2955560391125155044","pictures":"https://scontent-iad3-1.cdninstagram.com/v/t51.2885-15/312470744_903848123933572_2217213726367316729_n.webp?stp=dst-jpg_e35&_nc_ht=scontent-iad3-1.cdninstagram.com&_nc_cat=104&_nc_ohc=DO1VHbHytAEAX9VuUhr&edm=APU89FABAAAA&ccb=7-5&ig_cache_key=Mjk1NTU2MDM4NjQ5NDYyMTMwMg%3D%3D.2-ccb7-5&oh=00_AfCV-yNhztVNs6MvBg7Xbk1pdwiK9qkXZBvyJ3m0j4-png&oe=645A5D17&_nc_sid=86f79a"},{"id":"2955558118399507789","pictures":"https://scontent-iad3-2.cdninstagram.com/v/t51.2885-15/312387641_5439158246213850_6490213931569138585_n.webp?stp=dst-jpg_e35&_nc_ht=scontent-iad3-2.cdninstagram.com&_nc_cat=106&_nc_ohc=-URzZ-hhCjYAX-ex2ir&edm=APU89FABAAAA&ccb=7-5&ig_cache_key=Mjk1NTU1ODExNDA5NjE4Njc1Mw%3D%3D.2-ccb7-5&oh=00_AfAInyhlhhFYFiFWd3zj3LMBvo6qtAKPhQhEydnqh3Pq9Q&oe=6459FEE6&_nc_sid=86f79a"},{"id":"2947583823832525156","pictures":"https://scontent-iad3-1.cdninstagram.com/v/t51.2885-15/311173256_8417209341652624_3000575915030618118_n.webp?stp=dst-jpg_e35&_nc_ht=scontent-iad3-1.cdninstagram.com&_nc_cat=104&_nc_ohc=zOCIacZZ93UAX-VLag3&edm=APU89FABAAAA&ccb=7-5&ig_cache_key=Mjk0NzU4MzgyMzgzMjUyNTE1Ng%3D%3D.2-ccb7-5&oh=00_AfAsDq0pUiaE2g9TPLFv8NFo5lEk7FYURMn_yFzfJZjp2g&oe=645B3E2E&_nc_sid=86f79a"}]